iqm/qiskit_iqm/__init__.py
iqm/qiskit_iqm/iqm_backend.py
iqm/qiskit_iqm/iqm_circuit.py
iqm/qiskit_iqm/iqm_circuit_validation.py
iqm/qiskit_iqm/iqm_job.py
iqm/qiskit_iqm/iqm_move_layout.py
iqm/qiskit_iqm/iqm_naive_move_pass.py
iqm/qiskit_iqm/iqm_provider.py
iqm/qiskit_iqm/iqm_transpilation.py
iqm/qiskit_iqm/move_gate.py
iqm/qiskit_iqm/py.typed
iqm/qiskit_iqm/qiskit_to_iqm.py
iqm/qiskit_iqm/transpiler_plugins.py
iqm/qiskit_iqm/examples/__init__.py
iqm/qiskit_iqm/examples/bell_measure.py
iqm/qiskit_iqm/examples/resonance_example.py
iqm/qiskit_iqm/examples/transpile_example.py
iqm/qiskit_iqm/fake_backends/__init__.py
iqm/qiskit_iqm/fake_backends/fake_adonis.py
iqm/qiskit_iqm/fake_backends/fake_aphrodite.py
iqm/qiskit_iqm/fake_backends/fake_apollo.py
iqm/qiskit_iqm/fake_backends/fake_deneb.py
iqm/qiskit_iqm/fake_backends/fake_garnet.py
iqm/qiskit_iqm/fake_backends/iqm_fake_backend.py
qiskit_iqm-18.2.dist-info/licenses/AUTHORS.rst
qiskit_iqm-18.2.dist-info/licenses/LICENSE
qiskit_iqm-18.2.dist-info/METADATA
qiskit_iqm-18.2.dist-info/WHEEL
qiskit_iqm-18.2.dist-info/entry_points.txt
qiskit_iqm-18.2.dist-info/top_level.txt
qiskit_iqm-18.2.dist-info/RECORD
