Metadata-Version: 2.4
Name: qiskit-iqm
Version: 18.2
Summary: Qiskit adapter for IQM's quantum architectures
Author-email: IQM Finland Oy <developers@meetiqm.com>
License:                                  Apache License
Project-URL: homepage, https://github.com/iqm-finland/qiskit-on-iqm
Project-URL: documentation, https://iqm-finland.github.io/qiskit-on-iqm
Project-URL: repository, https://github.com/iqm-finland/qiskit-on-iqm.git
Project-URL: changelog, https://github.com/iqm-finland/qiskit-on-iqm/blob/main/CHANGELOG.rst
Classifier: Development Status :: 4 - Beta
Classifier: Programming Language :: Python :: 3 :: Only
Classifier: Topic :: Scientific/Engineering :: Physics
Classifier: Intended Audience :: Science/Research
Classifier: License :: OSI Approved :: Apache Software License
Requires-Python: <3.13,>=3.10
License-File: LICENSE
License-File: AUTHORS.rst
Requires-Dist: numpy
Requires-Dist: qiskit<1.3,>=1.0
Requires-Dist: qiskit-aer<0.16,>=0.13.1
Requires-Dist: iqm-client<22.10,>=22.9
Provides-Extra: dev
Requires-Dist: tox==4.11.4; extra == "dev"
Provides-Extra: docs
Requires-Dist: sphinx==7.2.6; extra == "docs"
Requires-Dist: sphinx-book-theme==1.1.2; extra == "docs"
Provides-Extra: testing
Requires-Dist: black==24.10.0; extra == "testing"
Requires-Dist: isort==5.13.2; extra == "testing"
Requires-Dist: pylint==3.3.3; extra == "testing"
Requires-Dist: mypy==1.14.1; extra == "testing"
Requires-Dist: mockito==1.4.0; extra == "testing"
Requires-Dist: pytest==8.3.4; extra == "testing"
Requires-Dist: pytest-cov==6.0.0; extra == "testing"
Requires-Dist: pytest-pylint==0.21.0; extra == "testing"
Requires-Dist: types-Jinja2==2.11.9; extra == "testing"
Dynamic: license-file
